setup.py
chen_bilibili_download/ChenBilibiliVideo.py
chen_bilibili_download/ChenSpiderBasicInfo.py
chen_bilibili_download/__init__.py
chen_bilibili_download.egg-info/PKG-INFO
chen_bilibili_download.egg-info/SOURCES.txt
chen_bilibili_download.egg-info/dependency_links.txt
chen_bilibili_download.egg-info/top_level.txt