Metadata-Version: 2.2
Name: chen_bilibili_download
Version: 1.0.2
Summary: This is a bilibili down class with search and download functions
Author: Chen_Station_B_Cuadaa
Author-email: 
Keywords: python,bilibili,download,windows
Classifier: Development Status :: 1 - Planning
Classifier: Intended Audience :: Developers
Classifier: Programming Language :: Python :: 3
Classifier: Operating System :: Microsoft :: Windows
Dynamic: author
Dynamic: classifier
Dynamic: description
Dynamic: description-content-type
Dynamic: keywords
Dynamic: summary
